Metadata-Version: 2.1
Name: zenoml
Version: 0.6.4
Summary: Interactive Evaluation Framework for Machine Learning
Home-page: https://zenoml.com
License: MIT
Keywords: ml,testing,evaluation,machine learning,ai
Author: Ángel Alexander Cabrera
Author-email: alex.cabrera@gmail.com
Requires-Python: >=3.8,<4.0
Classifier: License :: OSI Approved :: MIT License
Classifier: Programming Language :: Python :: 3
Classifier: Programming Language :: Python :: 3.8
Classifier: Programming Language :: Python :: 3.9
Classifier: Programming Language :: Python :: 3.10
Classifier: Programming Language :: Python :: 3.11
Requires-Dist: fastapi (>=0.95.1,<0.101.0)
Requires-Dist: inquirer (>=3.1.2,<4.0.0)
Requires-Dist: nest-asyncio (>=1.5.6,<2.0.0)
Requires-Dist: opentsne (>=0.7.1,<1.1.0)
Requires-Dist: pandas (>=2.0.0,<3.0.0)
Requires-Dist: pathos (>=0.3.0,<0.4.0)
Requires-Dist: pydantic (<2.0.0)
Requires-Dist: requests (>=2.28.1,<3.0.0)
Requires-Dist: setuptools
Requires-Dist: tomli (>=2.0.1,<3.0.0)
Requires-Dist: tqdm (>=4.64.0,<5.0.0)
Requires-Dist: uvicorn (>=0.22,<0.24)
Requires-Dist: websockets (>=11.0,<12.0)
Requires-Dist: zeno-sliceline (>=0.0.1,<0.0.2)
Project-URL: Repository, https://github.com/zeno-ml/zeno
